odoo/addons/ssi_service_quotation_custom_information/README.rst
odoo/addons/ssi_service_quotation_custom_information/__init__.py
odoo/addons/ssi_service_quotation_custom_information/__manifest__.py
odoo/addons/ssi_service_quotation_custom_information/models/__init__.py
odoo/addons/ssi_service_quotation_custom_information/models/service_quotation.py
odoo/addons/ssi_service_quotation_custom_information/static/description/icon.png
odoo14_addon_ssi_service_quotation_custom_information-14.0.1.0.0.dist-info/METADATA
odoo14_addon_ssi_service_quotation_custom_information-14.0.1.0.0.dist-info/WHEEL
odoo14_addon_ssi_service_quotation_custom_information-14.0.1.0.0.dist-info/top_level.txt
odoo14_addon_ssi_service_quotation_custom_information-14.0.1.0.0.dist-info/RECORD
